





{
  "14-B-2": [
    {
      "metadane": [
        
        {
                        "nazwa": "14.B.2 Udział pracujących w gospodarce morskiej w ogólnej liczbie pracujących w województwie",
                      
                        "cel": "Cel 14. Życie pod wodą",
                      
                        "priorytet": "Zwiększenie udziału sektora gospodarki morskiej w PKB oraz wzrostu zatrudnienia w gospodarce morskiej",
                      
                        "definicja": "Udział liczby pracujących w działalnościach zaliczanych do gospodarki morskiej w ogólnej liczbie pracujących w województwie.",
                      
                        "jednostka": "procent",
                      
                        "wymiary": "ogółem",
                      
                        "metodologia": "Gospodarka morska – do gospodarki morskiej zalicza się działalność gospodarczą obejmującą eksploatację portów morskich, żeglugę morską, budownictwo okrętowe. Pracujący – osoby wykonujące pracę przynoszącą im zarobek (w formie wynagrodzenia za pracę) lub dochód.",
                      
                        "zrodlo": "Główny Urząd Statystyczny",
                      
                        "czestotliwosc": "Dane roczne; od 2010 r.",
                      
                        "uwagi": "",
                      
                        "data_aktualizacji_danych": "",
                      
                        "data_aktualizacji_metadanych": ""
                      }
      ],
      "dane": [
        {
                      "województwa": [
                          {
                              "Polska": [
                                  {
                                  }
                              ],
                              "Dolnośląskie": [
                                  {
                                  }
                              ],
                              "Kujawsko-Pomorskie": [
                                  {
                                  }
                              ],
                              "Lubelskie": [
                                  {
                                  }
                              ],
                              "Lubuskie": [
                                  {
                                  }
                              ],
                              "Łódzkie": [
                                  {
                                  }
                              ],
                              "Małopolskie": [
                                  {
                                  }
                              ],
                              "Mazowieckie": [
                                  {
                                  }
                              ],
                              "Opolskie": [
                                  {
                                  }
                              ],
                              "Podkarpackie": [
                                  {
                                  }
                              ],
                              "Podlaskie": [
                                  {
                                  }
                              ],
                              "Pomorskie": [
                                  {
                                  }
                              ],
                              "Śląskie": [
                                  {
                                  }
                              ],
                              "Świętokrzyskie": [
                                  {
                                  }
                              ],
                              "Warmińsko-Mazurskie": [
                                  {
                                  }
                              ],
                              "Wielkopolskie": [
                                  {
                                  }
                              ],
                              "Zachodniopomorskie": [
                                  {
                                  }
                              ]
                          }
                      ]}
      ]
    }
  ]
}
