


{
  "2-b-1": [
    {
      "metadata": [
        
        {
                        "name": "2.b.1 Agricultural export subsidies",
                      
                        "goal": "Goal 2. Zero hunger",
                      
                        "target": "2.b Correct and prevent trade restrictions and distortions in world agricultural markets, including through the parallel elimination of all forms of agricultural export subsidies and all export measures with equivalent effect, in accordance with the mandate of the Doha Development Round",
                      
                        "definition": "",
                      
                        "unit": "",
                      
                        "dimensions": "",
                      
                        "methodology": "",
                      
                        "source": "",
                      
                        "availability": "",
                      
                        "notes": "",
                      
                        "data_updated_on": "",
                      
                        "metadata_updated_on": "19-12-2019"
                      }
      ],
      "data": [
        {}
      ]
    }
  ]
}
